pyquotes/__init__.py
pyquotes/cli.py
pyquotes/quotes.py
pyquotes/settings.py
pyquotes/transform.py
pyquotes-1.0.0.dist-info/LICENSE
pyquotes-1.0.0.dist-info/METADATA
pyquotes-1.0.0.dist-info/WHEEL
pyquotes-1.0.0.dist-info/entry_points.txt
pyquotes-1.0.0.dist-info/top_level.txt
pyquotes-1.0.0.dist-info/RECORD
